color_picker/__init__.py
color_picker/color_picker.py
color_picker/wheel_maker.py
circuitpython_Color_Picker-0.4.3.dist-info/LICENSE
circuitpython_Color_Picker-0.4.3.dist-info/METADATA
circuitpython_Color_Picker-0.4.3.dist-info/WHEEL
circuitpython_Color_Picker-0.4.3.dist-info/top_level.txt
circuitpython_Color_Picker-0.4.3.dist-info/RECORD
