Metadata-Version: 2.1
Name: circuitpython-Color-Picker
Version: 0.4.3
Summary: Colopicker en CircuitPython for TFT displays
Home-page: https://github.com/jposada202020/CircuitPython_color_picker.git
Author: Jose David M.
Author-email: "Jose D. Montoya" <colorpicker@mailmeto.mozmail.com>
License: MIT
Project-URL: Homepage, https://github.com/jposada202020/CircuitPython_color_picker.git
Keywords: hardware,micropython,circuitpython,graphic,wheel,widget,displayio,color,widget,themes
Classifier: Intended Audience :: Developers
Classifier: Topic :: Software Development :: Libraries
Classifier: Topic :: Software Development :: Embedded Systems
Classifier: Topic :: System :: Hardware
Classifier: License :: OSI Approved :: MIT License
Classifier: Programming Language :: Python :: 3
License-File: LICENSE
Requires-Dist: Adafruit-Blinka
Requires-Dist: Adafruit-Blinka-Displayio
Requires-Dist: Adafruit-CircuitPython-Displayio-Layout
Provides-Extra: optional
